.travis.yml
CHANGELOG.md
LICENSE
MANIFEST.in
README.rst
USAGE.rst
appveyor.yml
pytest.ini
requirements-docs.txt
requirements-flake.txt
requirements-tests.txt
setup.cfg
setup.py
tox.ini
.circleci/config.yml
logs/.gitkeep
qatestlink/__init__.py
qatestlink.egg-info/PKG-INFO
qatestlink.egg-info/SOURCES.txt
qatestlink.egg-info/dependency_links.txt
qatestlink.egg-info/requires.txt
qatestlink.egg-info/top_level.txt
qatestlink/configs/__init__.py
qatestlink/configs/settings.json
qatestlink/core/__init__.py
qatestlink/core/logger_manager.py
qatestlink/core/testlink_manager.py
qatestlink/core/utils.py
qatestlink/core/connections/__init__.py
qatestlink/core/connections/connection_base.py
qatestlink/core/exceptions/__init__.py
qatestlink/core/exceptions/response_exception.py
qatestlink/core/models/__init__.py
qatestlink/core/models/tl_models.py
qatestlink/core/models/tl_reports.py
qatestlink/core/xmls/__init__.py
qatestlink/core/xmls/route_type.py
qatestlink/core/xmls/xmlrpc_manager.py
tests/__init__.py
tests/reports/__init__.py
tests/unitaries/__init__.py
tests/unitaries/suite_001_connections.py
tests/unitaries/suite_002_methods.py