Metadata-Version: 1.1
Name: qatestlink
Version: 0.1.2
Summary: Main automation lib
Home-page: https://github.com/netzulo/qatestlink
Author: Netzulo Open Source
Author-email: netzuleando@gmail.com
License:                     GNU GENERAL PUBLIC LICENSE
